on_chip/APB/apb_slave.v
module apb_slave #(
                   parameter DATA_WIDTH = 8,
                   parameter ADDR_WIDTH = 16 )

                   (input pclk, presetn,
                    input psel, pwrite, penable,
                    input [DATA_WIDTH-1:0] pwdata,
                    input [ADDR_WIDTH-1:0] paddr,
                    output reg pready, pslverr,
                    output reg [DATA_WIDTH-1:0] prdata);

                reg[DATA_WIDTH-1:0] mem [0:15];

                always @(posedge pclk or negedge presetn) begin
                    if(!presetn) begin
                        pready <= 0;
                        pslverr <= 0;
                        prdata <= 0;

                        for(integer i=0; i<16; i=i+1) begin
                            mem[i] <= 0;
                        end
                    end else begin
                            pready <= 1;
                            pslverr <= 0;

                            if(psel && penable) begin

                                if(pwrite)
                                    mem[paddr] <= pwdata;
                                else
                                    prdata <= mem[paddr];
                            
                            end
                            
                        end
                    end
                    endmodule

on_chip/APB/apb_master.v
module apb_master #(
                    parameter DATA_WIDTH = 8,
                    parameter ADDR_WIDTH = 16)
                                                  
                    (input pclk, presetn,           
                     input transfer, write_en,              // User side control
                     input [ADDR_WIDTH-1:0] addr,
                     input [DATA_WIDTH-1:0] write_data,
                     input pready, pslverr,                 // APB slave side
                     input [DATA_WIDTH-1:0] prdata,

                     output reg [ADDR_WIDTH-1:0] paddr,     // APB outputs    
                     output reg [DATA_WIDTH-1:0] pwdata,
                     output reg psel, penable, pwrite,
                     output reg [DATA_WIDTH-1:0] read_data  //captured read data
                 );


//--------------------------------------------------
// STATE DECLARATION
//--------------------------------------------------

localparam [1:0]
IDLE = 2'b00,
SETUP = 2'b01,
ACCESS = 2'b10;

reg [1:0] current_state, next_state;

//--------------------------------------------------
// STATE REGISTER LOGIC
//--------------------------------------------------


always @(posedge pclk or negedge presetn) begin
    if(!presetn) begin
        current_state <= IDLE;
      
    end else begin
        current_state <= next_state;
        if(psel && penable && pready && !pwrite)
                read_data <= prdata;
        end
    end

//--------------------------------------------------
// NEXT STATE LOGIC
//--------------------------------------------------

always @(*) begin
    next_state = current_state;
    
    case(current_state)
        IDLE: begin
            if(transfer)
                next_state = SETUP;
            else
                next_state = IDLE;
        end

        SETUP: begin
            next_state = ACCESS;
        end

        ACCESS: begin
            if(pready) begin
                if(transfer)
                    next_state = SETUP;
                else
                    next_state = IDLE;
            end else begin
               next_state = ACCESS;
           end
       end

       default: begin
          next_state = IDLE;
      end
  endcase
  end
//--------------------------------------------------
//  OUTPUT LOGIC
//--------------------------------------------------
always @(posedge pclk or negedge presetn) begin
    if (!presetn) begin
        paddr <= 0;
        pwdata <= 0;
        penable <= 0;
        psel <= 0;
        pwrite <= 0;
        read_data <= 0;
    end
    else begin

        case(next_state)
            IDLE: begin
                paddr <= 0;
                pwdata <= 0;
                penable <= 0;
                psel <= 0;
                pwrite <= 0;
            end

            SETUP: begin
                psel <= 1;
                penable <= 0;

                pwrite <= write_en;
                paddr <= addr;

                if(write_en)
                    pwdata <= write_data;
                else 
                    pwdata <= 0;
            end

            ACCESS: begin
                psel <= 1;
                penable <= 1;

                    end

            default:
            begin
                psel    <= 0;
                penable <= 0;
                pwrite  <= 0;
                paddr   <= 0;
                pwdata  <= 0;
            end
        endcase
    end
end  

endmodule

on_chip/APB/apb_top.v
module apb_top #(parameter ADDR_WIDTH = 16,
                 parameter DATA_WIDTH = 8)
    
               
               (input pclk, presetn, transfer, write_en,
                input [ADDR_WIDTH-1:0] addr,
                input [DATA_WIDTH-1:0] write_data,
                output [DATA_WIDTH-1:0] read_data);

                wire psel, penable, pwrite;
                wire [15:0] paddr;            
                wire pready, pslverr;
                wire [7:0] pwdata, prdata;
                
                apb_master inst_m 
                (
                    //board inputs and user side controlls
                    .pclk(pclk), .presetn(presetn), .transfer(transfer), .write_en(write_en), .addr(addr), .write_data(write_data),
                    //outputs from master, inputs to slave
                    .psel(psel),.penable(penable),.pwrite(pwrite),.paddr(paddr),.pwdata(pwdata),
                    //outputs from slave, inputs to master
                    .pready(pready),.pslverr(pslverr),.prdata(prdata),
                    //read data from slave
                    .read_data(read_data)
                );

                apb_slave inst_s 
                (
                    //board inputs
                    .pclk(pclk), .presetn(presetn),
                    //outputs from master, inputs to slave 
                    .psel(psel),.penable(penable),.pwrite(pwrite),.paddr(paddr),.pwdata(pwdata),
                    //outputs from slave, inputs to master
                    .pready(pready),.pslverr(pslverr),.prdata(prdata) 
                );

                endmodule

on_chip/APB/apb_tb.v
module apb_tb;

reg pclk, presetn, transfer, write_en;
reg [7:0] write_data;
reg [15:0] addr;
wire [7:0] read_data;

apb_top dut (.pclk(pclk),.presetn(presetn),.transfer(transfer),.write_en(write_en),.write_data(write_data),.addr(addr),.read_data(read_data));

always #5 pclk = ~pclk;

task apb_write;

    input [15:0] wr_addr;
    input [7:0] wr_data;

    begin
        transfer = 1;
        write_en =1;
        
        addr = wr_addr;
        write_data = wr_data;
        @(posedge pclk);
        @(posedge pclk);
        @(posedge pclk);

        transfer = 0;
    
    end

endtask

task apb_read;

    input [15:0] rd_addr;

    begin
            transfer = 1;
            write_en = 0;

            addr = rd_addr;
        @(posedge pclk);            
        @(posedge pclk);
        @(posedge pclk);    

            transfer = 0;

        end

    endtask


initial begin
pclk =0; presetn =0; transfer =0; write_en =0; write_data=0; addr=0; 
#20; presetn = 1;

 apb_write (16'h0f, 8'hA1);

#20; apb_read (16'h0f);

#50; $finish;

end

initial begin
    $dumpfile("apb_top.vcd");
    $dumpvars(0);
end

endmodule

on_chip/APB/apb_top.vcd
$date
	Mon Jul 13 13:58:44 2026
$end
$version
	Icarus Verilog
$end
$timescale
	1s
$end
$scope module apb_tb $end
$var wire 8 ! read_data [7:0] $end
$var reg 16 " addr [15:0] $end
$var reg 1 # pclk $end
$var reg 1 $ presetn $end
$var reg 1 % transfer $end
$var reg 8 & write_data [7:0] $end
$var reg 1 ' write_en $end
$scope module dut $end
$var wire 16 ( addr [15:0] $end
$var wire 1 # pclk $end
$var wire 1 $ presetn $end
$var wire 1 % transfer $end
$var wire 8 ) write_data [7:0] $end
$var wire 1 ' write_en $end
$var wire 8 * read_data [7:0] $end
$var wire 1 + pwrite $end
$var wire 8 , pwdata [7:0] $end
$var wire 1 - pslverr $end
$var wire 1 . psel $end
$var wire 1 / pready $end
$var wire 8 0 prdata [7:0] $end
$var wire 1 1 penable $end
$var wire 16 2 paddr [15:0] $end
$var parameter 32 3 ADDR_WIDTH $end
$var parameter 32 4 DATA_WIDTH $end
$scope module inst_m $end
$var wire 16 5 addr [15:0] $end
$var wire 1 # pclk $end
$var wire 1 $ presetn $end
$var wire 1 % transfer $end
$var wire 8 6 write_data [7:0] $end
$var wire 1 ' write_en $end
$var wire 1 - pslverr $end
$var wire 1 / pready $end
$var wire 8 7 prdata [7:0] $end
$var parameter 2 8 ACCESS $end
$var parameter 32 9 ADDR_WIDTH $end
$var parameter 32 : DATA_WIDTH $end
$var parameter 2 ; IDLE $end
$var parameter 2 < SETUP $end
$var reg 2 = current_state [1:0] $end
$var reg 2 > next_state [1:0] $end
$var reg 16 ? paddr [15:0] $end
$var reg 1 1 penable $end
$var reg 1 . psel $end
$var reg 8 @ pwdata [7:0] $end
$var reg 1 + pwrite $end
$var reg 8 A read_data [7:0] $end
$upscope $end
$scope module inst_s $end
$var wire 16 B paddr [15:0] $end
$var wire 1 # pclk $end
$var wire 1 1 penable $end
$var wire 1 $ presetn $end
$var wire 1 . psel $end
$var wire 8 C pwdata [7:0] $end
$var wire 1 + pwrite $end
$var parameter 32 D ADDR_WIDTH $end
$var parameter 32 E DATA_WIDTH $end
$var reg 8 F prdata [7:0] $end
$var reg 1 / pready $end
$var reg 1 - pslverr $end
$scope begin $ivl_for_loop0 $end
$var integer 32 G i [31:0] $end
$upscope $end
$upscope $end
$upscope $end
$scope task apb_read $end
$var reg 16 H rd_addr [15:0] $end
$upscope $end
$scope task apb_write $end
$var reg 16 I wr_addr [15:0] $end
$var reg 8 J wr_data [7:0] $end
$upscope $end
$upscope $end
$enddefinitions $end
$comment Show the parameter values. $end
$dumpall
b1000 E
b10000 D
b1 <
b0 ;
b1000 :
b10000 9
b10 8
b1000 4
b10000 3
$end
#0
$dumpvars
bx J
bx I
bx H
b10000 G
b0 F
b0 C
b0 B
b0 A
b0 @
b0 ?
b0 >
b0 =
b0 7
b0 6
b0 5
b0 2
01
b0 0
0/
0.
0-
b0 ,
0+
b0 *
b0 )
b0 (
0'
b0 &
0%
0$
0#
b0 "
b0 !
$end
#5
b10000 G
1#
#10
0#
#15
b10000 G
1#
#20
b1 >
0#
b10100001 &
b10100001 )
b10100001 6
b1111 "
b1111 (
b1111 5
1'
1%
b10100001 J
b1111 I
1$
#25
b10 >
b10100001 ,
b10100001 @
b10100001 C
b1111 2
b1111 ?
b1111 B
1+
1.
b1 =
1/
1#
#30
0#
#35
b1 >
b10 =
11
1#
#40
0#
#45
01
b1 =
b10 >
0%
1#
#50
0#
#55
b0 >
b10 =
11
1#
#60
0#
#65
b0 ,
b0 @
b0 C
0+
01
b1 =
b10 >
1#
0'
1%
b1111 H
#70
0#
#75
b1 >
b10 =
11
1#
#80
0#
#85
01
b1 =
b10100001 0
b10100001 7
b10100001 F
b10 >
0%
1#
#90
0#
#95
b0 >
b10 =
11
1#
#100
0#
#105
0.
01
b0 2
b0 ?
b0 B
b10100001 !
b10100001 *
b10100001 A
b0 =
1#
